{
  "meta": {
    "code": "MOP",
    "createdAt": "2024-07-22T10:46:27Z"
  },
  "data": {
    "AFN": null,
    "ALL": 0.08733762548,
    "DZD": 0.059775517429999994,
    "AOA": 0.009209080932,
    "ARS": null,
    "AMD": null,
    "AWG": 4.464674997,
    "AUD": 5.355783858000001,
    "AZN": 4.727157025,
    "BSD": 8.043809394,
    "BHD": null,
    "BDT": null,
    "BBD": 3.9857363200000004,
    "BYN": null,
    "BZD": null,
    "XOF": 0.013346176849999999,
    "BMD": null,
    "BTN": 0.09615426501999999,
    "BOB": 1.164844817,
    "BAM": 4.476341905,
    "BWP": 0.5940397328,
    "BRL": null,
    "BND": null,
    "BGN": 4.475464757,
    "BIF": 0.0027929762689999998,
    "CVE": 0.07939600398999999,
    "KHR": 0.0019586091759999998,
    "XAF": 0.013346176849999999,
    "CAD": 5.846432035,
    "KYD": 9.656869015,
    "CLP": null,
    "CNY": 1.10477929,
    "COP": 0.001985947413,
    "KMF": 0.01774969902,
    "CDF": 0.002830340428,
    "CRC": null,
    "HRK": null,
    "CUP": 0.3351416747,
    "CZK": 0.3470136649,
    "DKK": 1.172745976,
    "DJF": 0.04519966237,
    "DOP": 0.1358775206,
    "EGP": 0.1658334582,
    "ERN": null,
    "SZL": 0.43847143320000004,
    "ETB": 0.14031340450000002,
    "EUR": 8.75078315,
    "FJD": null,
    "GMD": null,
    "GEL": 2.9601655090000003,
    "GHS": 0.5212945008000001,
    "GIP": null,
    "GTQ": 1.035768706,
    "GNF": 0.0009345515761,
    "GYD": 0.03852056289,
    "HTG": null,
    "HNL": null,
    "HKD": 1.029272269,
    "HUF": null,
    "ISK": null,
    "INR": null,
    "IDR": 0.0004955751501,
    "IRR": null,
    "IQD": 0.00614285168,
    "ILS": null,
    "JMD": null,
    "JPY": null,
    "JOD": null,
    "KZT": 0.01688293412,
    "KES": 0.06134478556,
    "KWD": 26.28715409,
    "KGS": null,
    "LAK": null,
    "LBP": null,
    "LSL": 0.43857357290000004,
    "LRD": null,
    "LYD": null,
    "MOP": null,
    "MKD": null,
    "MGA": 0.001785728723,
    "MWK": null,
    "MYR": 1.7169463660000002,
    "MVR": 0.5235509761,
    "MRU": 0.2038371348,
    "MUR": null,
    "MXN": 0.4471020355,
    "MDL": null,
    "MNT": null,
    "MAD": 0.8171238894,
    "MZN": 0.1257746122,
    "MMK": null,
    "NAD": 0.43857357290000004,
    "NPR": 0.06009755075,
    "ANG": null,
    "TWD": 0.24461513740000002,
    "NZD": 4.823186890000001,
    "NIO": 0.21854721800000002,
    "NGN": null,
    "KPW": null,
    "NOK": 0.7353856240000001,
    "OMR": 20.87867708,
    "PKR": 0.028923105259999998,
    "PAB": 8.047795333,
    "PGK": null,
    "PYG": 0.001063998154,
    "PEN": 2.148889538,
    "PHP": 0.1375797415,
    "PLN": null,
    "QAR": 2.2038565990000003,
    "RON": null,
    "RUB": 0.09148075173999999,
    "RWF": 0.006139463632,
    "SHP": 10.37670063,
    "WST": null,
    "STN": null,
    "SAR": null,
    "RSD": 0.07474808831,
    "SCR": 0.5963971424,
    "SLL": null,
    "SGD": 5.97615586,
    "SBD": 0.9502767477,
    "SOS": 0.014133239039999999,
    "ZAR": 0.4402895356,
    "KRW": 0.005790412718,
    "SSP": null,
    "LKR": null,
    "SDG": 0.01371359522,
    "SRD": null,
    "SEK": 0.7534931977,
    "CHF": null,
    "SYP": null,
    "TJS": 0.7563989953,
    "TZS": 0.002993378264,
    "THB": 0.2215040854,
    "TOP": 3.38965524,
    "TTD": null,
    "TND": 2.5944937930000003,
    "TRY": 0.24358715090000002,
    "TMT": null,
    "UGX": 0.0021769510299999998,
    "UAH": 0.1938637694,
    "AED": null,
    "GBP": 10.39663033,
    "USD": 8.036166999999999,
    "UYU": 0.1994576649,
    "UZS": null,
    "VUV": null,
    "VES": 0.21980307000000002,
    "VND": 0.0003171963512,
    "YER": 0.03209991458,
    "ZMW": null,
    "ZWL": null
  }
}