{
  "meta": {
    "code": "BAM",
    "createdAt": "2024-07-22T08:34:40Z"
  },
  "data": {
    "AFN": 0.025419571909999997,
    "ALL": null,
    "DZD": null,
    "AOA": null,
    "ARS": null,
    "AMD": 0.004654794595,
    "AWG": null,
    "AUD": null,
    "AZN": null,
    "BSD": null,
    "BHD": null,
    "BDT": null,
    "BBD": 0.8904235584,
    "BYN": null,
    "BZD": null,
    "XOF": null,
    "BMD": null,
    "BTN": 0.021481105599999998,
    "BOB": 0.2602292735,
    "BAM": null,
    "BWP": null,
    "BRL": 0.3199371814,
    "BND": 1.3362148600000001,
    "BGN": null,
    "BIF": 0.0006239081137,
    "CVE": null,
    "KHR": null,
    "XAF": 0.002981569609,
    "CAD": 1.3069873760000001,
    "KYD": null,
    "CLP": 0.001903018,
    "CNY": 0.2468104832,
    "COP": null,
    "KMF": 0.003965327583,
    "CDF": null,
    "CRC": null,
    "HRK": null,
    "CUP": 0.0748714964,
    "CZK": 0.07751870215,
    "DKK": null,
    "DJF": null,
    "DOP": null,
    "EGP": 0.037109152609999994,
    "ERN": null,
    "SZL": 0.09795562537,
    "ETB": 0.031370568759999995,
    "EUR": 1.955350995,
    "FJD": 0.80105137,
    "GMD": 0.026479350059999997,
    "GEL": null,
    "GHS": 0.1164585078,
    "GIP": null,
    "GTQ": 0.23139334450000001,
    "GNF": null,
    "GYD": null,
    "HTG": 0.013613673719999999,
    "HNL": null,
    "HKD": 0.22993232930000002,
    "HUF": 0.005012892314,
    "ISK": null,
    "INR": 0.021459292709999998,
    "IDR": 0.0001106147165,
    "IRR": 0.00004265130295,
    "IQD": null,
    "ILS": null,
    "JMD": 0.011498515349999999,
    "JPY": null,
    "JOD": null,
    "KZT": null,
    "KES": null,
    "KWD": null,
    "KGS": 0.02121033307,
    "LAK": 0.00008104127824,
    "LBP": null,
    "LSL": 0.09797844364,
    "LRD": 0.00920757791,
    "LYD": 0.3726130787,
    "MOP": 0.2235191587,
    "MKD": 0.0317124844,
    "MGA": 0.0003989363059,
    "MWK": 0.001036290247,
    "MYR": 0.3835292208,
    "MVR": 0.1169626101,
    "MRU": 0.045537730639999996,
    "MUR": null,
    "MXN": 0.0997253244,
    "MDL": null,
    "MNT": null,
    "MAD": 0.1825475402,
    "MZN": null,
    "MMK": 0.0005527687408,
    "NAD": 0.09797844364,
    "NPR": null,
    "ANG": 0.9976821411000001,
    "TWD": 0.05464395901,
    "NZD": null,
    "NIO": 0.04883160345,
    "NGN": 0.0010791839129999999,
    "KPW": null,
    "NOK": 0.164662223,
    "OMR": null,
    "PKR": 0.006466483126,
    "PAB": null,
    "PGK": null,
    "PYG": null,
    "PEN": null,
    "PHP": 0.030746433469999997,
    "PLN": 0.45655304830000004,
    "QAR": 0.4923471293,
    "RON": null,
    "RUB": null,
    "RWF": null,
    "SHP": null,
    "WST": null,
    "STN": null,
    "SAR": null,
    "RSD": null,
    "SCR": 0.1328939766,
    "SLL": 0.00009262181168,
    "SGD": null,
    "SBD": 0.212294225,
    "SOS": 0.003157401291,
    "ZAR": 0.09831825802,
    "KRW": 0.001293118324,
    "SSP": null,
    "LKR": 0.0059192584949999995,
    "SDG": 0.003063651802,
    "SRD": 0.060431532249999996,
    "SEK": 0.1684201629,
    "CHF": null,
    "SYP": null,
    "TJS": null,
    "TZS": null,
    "THB": null,
    "TOP": null,
    "TTD": 0.2646911326,
    "TND": null,
    "TRY": 0.0543616822,
    "TMT": 0.5124172189,
    "UGX": null,
    "UAH": 0.04330965562,
    "AED": 0.4887837102,
    "GBP": 2.3214755,
    "USD": 1.7953,
    "UYU": null,
    "UZS": null,
    "VUV": null,
    "VES": null,
    "VND": 0.00007089047251,
    "YER": 0.007171201974,
    "ZMW": 0.07039768061,
    "ZWL": null
  }
}